zjpf/__init__.py
zjpf/f.py
zjpf-0.0.4.dist-info/LICENSE
zjpf-0.0.4.dist-info/METADATA
zjpf-0.0.4.dist-info/WHEEL
zjpf-0.0.4.dist-info/top_level.txt
zjpf-0.0.4.dist-info/RECORD
